levers/__init__.py
levers/geometry.py
levers/motions.py
levers/selectors.py
levers/types.py
levers/renderers/__init__.py
levers/renderers/pygame_renderer.py
levers/renderers/pyqtgraph_renderer.py
levers/renderers/renderer.py
levers-0.2.0.dist-info/METADATA
levers-0.2.0.dist-info/WHEEL
levers-0.2.0.dist-info/licenses/LICENSE
levers-0.2.0.dist-info/RECORD
