Metadata-Version: 2.4
Name: levers
Version: 0.2.0
Summary: A Python package for visualizing lever mechanisms and animated geometry
Project-URL: Repository, https://github.com/a17sol/levers.git
Author-email: Michael Solovyev <solomisha57@gmail.com>
License-Expression: MIT
License-File: LICENSE
Keywords: animation,geometry,lever,mechanics,mechanism,simulation
Classifier: Development Status :: 3 - Alpha
Classifier: Intended Audience :: Education
Classifier: License :: OSI Approved :: MIT License
Classifier: Programming Language :: Python
Classifier: Programming Language :: Python :: 3
Classifier: Programming Language :: Python :: 3.12
Classifier: Programming Language :: Python :: 3.13
Classifier: Programming Language :: Python :: 3.14
Classifier: Programming Language :: Python :: 3.15
Classifier: Topic :: Scientific/Engineering :: Mathematics
Classifier: Topic :: Scientific/Engineering :: Visualization
Requires-Python: >=3.12
Provides-Extra: all
Requires-Dist: pygame; extra == 'all'
Requires-Dist: pyqt6; extra == 'all'
Requires-Dist: pyqtgraph; extra == 'all'
Provides-Extra: pygame
Requires-Dist: pygame; extra == 'pygame'
Provides-Extra: pyqt
Requires-Dist: pyqt6; extra == 'pyqt'
Requires-Dist: pyqtgraph; extra == 'pyqt'
